paradata/__init__.py
paradata/main.py
paradata/parser.py
paradata-0.1.7.dist-info/LICENSE
paradata-0.1.7.dist-info/METADATA
paradata-0.1.7.dist-info/WHEEL
paradata-0.1.7.dist-info/entry_points.txt
paradata-0.1.7.dist-info/top_level.txt
paradata-0.1.7.dist-info/RECORD
